excel_to_markdown_mcp/__init__.py
excel_to_markdown_mcp/server.py
excel_to_markdown_mcp-0.1.0.dist-info/METADATA
excel_to_markdown_mcp-0.1.0.dist-info/WHEEL
excel_to_markdown_mcp-0.1.0.dist-info/entry_points.txt
excel_to_markdown_mcp-0.1.0.dist-info/RECORD
