Metadata-Version: 2.4
Name: excel-to-markdown-mcp
Version: 0.1.0
Summary: Excel转Markdown MCP服务器 - Python版本
Requires-Python: >=3.11
Requires-Dist: markitdown>=0.0.1a3
Requires-Dist: mcp>=1.0.0
Requires-Dist: openpyxl>=3.0.0
Requires-Dist: pandas>=2.0.0
